deepreg/__init__.py
deepreg/callback.py
deepreg/download.py
deepreg/predict.py
deepreg/registry.py
deepreg/train.py
deepreg/util.py
deepreg/vis.py
deepreg/warp.py
deepreg/config/__init__.py
deepreg/config/parser.py
deepreg/config/v011.py
deepreg/dataset/__init__.py
deepreg/dataset/load.py
deepreg/dataset/preprocess.py
deepreg/dataset/util.py
deepreg/dataset/loader/__init__.py
deepreg/dataset/loader/grouped_loader.py
deepreg/dataset/loader/h5_loader.py
deepreg/dataset/loader/interface.py
deepreg/dataset/loader/nifti_loader.py
deepreg/dataset/loader/paired_loader.py
deepreg/dataset/loader/unpaired_loader.py
deepreg/dataset/loader/util.py
deepreg/loss/__init__.py
deepreg/loss/deform.py
deepreg/loss/image.py
deepreg/loss/label.py
deepreg/loss/util.py
deepreg/model/__init__.py
deepreg/model/layer.py
deepreg/model/layer_util.py
deepreg/model/network.py
deepreg/model/optimizer.py
deepreg/model/backbone/__init__.py
deepreg/model/backbone/global_net.py
deepreg/model/backbone/interface.py
deepreg/model/backbone/local_net.py
deepreg/model/backbone/u_net.py
deepreg-0.1.2.dist-info/LICENSE
deepreg-0.1.2.dist-info/METADATA
deepreg-0.1.2.dist-info/WHEEL
deepreg-0.1.2.dist-info/entry_points.txt
deepreg-0.1.2.dist-info/top_level.txt
deepreg-0.1.2.dist-info/RECORD
