Metadata-Version: 2.1
Name: deepreg
Version: 0.1.2
Summary: DeepReg is a freely available, community-supported open-source toolkit for research and education in medical image registration using deep learning.
Home-page: http://deepreg.net/
Author: DeepReg Development Team and Community
Author-email: deepregnet@gmail.com
License: apache-2.0
Keywords: Deep Learning,Image Fusion,Medical Image Registration,Neural Networks
Platform: UNKNOWN
Classifier: Development Status :: 5 - Production/Stable
Classifier: Environment :: Console
Classifier: Environment :: GPU
Classifier: Environment :: MacOS X
Classifier: Environment :: Win32 (MS Windows)
Classifier: Intended Audience :: Developers
Classifier: Intended Audience :: Education
Classifier: Intended Audience :: Science/Research
Classifier: License :: OSI Approved :: Apache Software License
Classifier: Natural Language :: English
Classifier: Operating System :: MacOS :: MacOS X
Classifier: Operating System :: Microsoft :: Windows :: Windows 10
Classifier: Operating System :: Unix
Classifier: Programming Language :: Python :: 3
Classifier: Topic :: Scientific/Engineering :: Artificial Intelligence
Classifier: Topic :: Scientific/Engineering :: Medical Science Apps.
Classifier: Topic :: Software Development
Requires-Dist: argparse
Requires-Dist: black (>=20.8b1)
Requires-Dist: flake8
Requires-Dist: GitPython
Requires-Dist: h5py (<2.11.0,>=2.10.0)
Requires-Dist: isort
Requires-Dist: m2r2 (>=0.2.6)
Requires-Dist: matplotlib
Requires-Dist: nibabel
Requires-Dist: notebook
Requires-Dist: numpy (==1.18.5)
Requires-Dist: pandas
Requires-Dist: pre-commit
Requires-Dist: pydocstyle
Requires-Dist: pylint
Requires-Dist: pytest
Requires-Dist: pytest-cov
Requires-Dist: pytest-dependency
Requires-Dist: pyyaml (>=5.3.1)
Requires-Dist: scipy
Requires-Dist: seed-isort-config
Requires-Dist: sphinx (==3.4.3)
Requires-Dist: sphinx-notfound-page
Requires-Dist: sphinx-rtd-theme
Requires-Dist: sphinx-tabs
Requires-Dist: tabulate
Requires-Dist: tensorboard-plugin-profile
Requires-Dist: tensorflow (==2.3.1)
Requires-Dist: testfixtures
Requires-Dist: tqdm
